{
  "A": { "type": "number" },
  "B": { "type": "number" },
  "G": { "type": "number" },
  "Offset": { "type": "number" },
  "R": { "type": "number" },
  "FontSize": { "type": "number" },
  "Text": { "type": "text" },
  "DTFormat": { "type": "text" },
  "archiveImages": { "type": "boolean" },
  "AeEnable": { "type": "boolean" },
  "AeMeteringMode": {
    "type": "select",
    "options": ["Centre Weighted", "Spot", "Matrix"]
  },
  "AnalogueGain": { "type": "number" },
  "ExposureTime": { "type": "number" },
  "ExposureValue": { "type": "number" },
  "HdrMode": {
    "type": "select",
    "options": ["Off", "Single Exposure", "Multi Exposure"]
  },
  "Sharpness": { "type": "number" },
  "NoiseReductionMode": {
    "type": "select",
    "options": ["Off", "Fast", "High Quality"]
  },
  "shotInterval": { "type": "number" },
  "type": { "type": "text" },
  "unsharpMask": { "type": "boolean" },
  "dawnOffset": { "type": "number" },
  "duskOffset": { "type": "number" },
  "elevation": { "type": "number" },
  "latitude": { "type": "number" },
  "longitude": { "type": "number" },
  "name": { "type": "text" },
  "sunRiseOffset": { "type": "number" },
  "sunSetOffset": { "type": "number" },
  "host": { "type": "text" },
  "password": { "type": "password" },
  "port": { "type": "number" },
  "username": { "type": "text" },
  "remoteUrl": { "type": "text" },
  "AwbMode": {
    "type": "select",
    "options": ["Auto", "Tungsten", "Fluorescent", "Indoor", "Daylight", "Cloudy"]
  },
  "enabled": { "type": "boolean" },
  "hflip": { "type": "boolean" },
  "vflip": { "type": "boolean" },
  "fps": { "type": "number" },
  "height": { "type": "number" },
  "width": { "type": "number" },
  "yt_api_key": { "type": "password" },
  "bitrate": { "type": "text" },
  "buffer": { "type": "text" },
  "filename": { "type": "text" },
  "folder": { "type": "text" },
  "timeout": { "type": "number" },
  "X": { "type": "number" },
  "Y": { "type": "number" },
  "scale": { "type": "number" },
  "opacity": { "type": "number" },
  "url": { "type": "text" },
  "onvif_w": { "type": "number" }
}
